bambi/__init__.py
bambi/config.py
bambi/formula.py
bambi/model_components.py
bambi/models.py
bambi/transformations.py
bambi/utils.py
bambi/backend/__init__.py
bambi/backend/links.py
bambi/backend/model_components.py
bambi/backend/pymc.py
bambi/backend/terms.py
bambi/backend/utils.py
bambi/data/__init__.py
bambi/data/datasets.py
bambi/defaults/__init__.py
bambi/defaults/distributions.py
bambi/defaults/families.py
bambi/defaults/hsgp.py
bambi/defaults/utils.py
bambi/families/__init__.py
bambi/families/family.py
bambi/families/likelihood.py
bambi/families/link.py
bambi/families/multivariate.py
bambi/families/univariate.py
bambi/interpret/__init__.py
bambi/interpret/create_data.py
bambi/interpret/effects.py
bambi/interpret/helpers.py
bambi/interpret/logs.py
bambi/interpret/plot_types.py
bambi/interpret/plotting.py
bambi/interpret/utils.py
bambi/plots/__init__.py
bambi/priors/__init__.py
bambi/priors/prior.py
bambi/priors/scaler.py
bambi/terms/__init__.py
bambi/terms/base.py
bambi/terms/common.py
bambi/terms/group_specific.py
bambi/terms/hsgp.py
bambi/terms/offset.py
bambi/terms/response.py
bambi/terms/utils.py
bambi-0.16.0.dist-info/licenses/LICENSE
bambi-0.16.0.dist-info/METADATA
bambi-0.16.0.dist-info/WHEEL
bambi-0.16.0.dist-info/top_level.txt
bambi-0.16.0.dist-info/RECORD
