Metadata-Version: 2.4
Name: bambi
Version: 0.16.0
Summary: BAyesian Model Building Interface in Python
Maintainer-email: Tomás Capretto <tomicapretto@gmail.com>, Osvaldo Martin <aloctavodia@gmail.com>, Gabriel Stechschulte <stechschulteg@gmail.com>, Ravin Kumar <ravinsdrive@gmail.com>
License: MIT License
Project-URL: homepage, https://bambinos.github.io/bambi
Project-URL: documentation, https://bambinos.github.io/bambi
Project-URL: repository, https://github.com/bambinos/bambi
Project-URL: changelog, https://github.com/bambinos/bambi/blob/main/CHANGELOG.md
Requires-Python: >=3.11
License-File: LICENSE
Requires-Dist: arviz>=0.20.0
Requires-Dist: formulae>=0.5.3
Requires-Dist: graphviz
Requires-Dist: pandas>=1.0.0
Requires-Dist: pymc>=5.26.1
Provides-Extra: jax
Requires-Dist: blackjax<1.3,>=1.2; extra == "jax"
Requires-Dist: jax<0.8,>=0.7; extra == "jax"
Requires-Dist: numpyro<0.20,>=0.19; extra == "jax"
Provides-Extra: nutpie
Requires-Dist: numba>=0.61.2; extra == "nutpie"
Requires-Dist: nutpie<0.16,>=0.15; extra == "nutpie"
Dynamic: license-file
